orpheus_cpp/__about__.py
orpheus_cpp/__init__.py
orpheus_cpp/__main__.py
orpheus_cpp/model.py
orpheus_cpp-0.0.3.dist-info/METADATA
orpheus_cpp-0.0.3.dist-info/WHEEL
orpheus_cpp-0.0.3.dist-info/licenses/LICENSE.txt
orpheus_cpp-0.0.3.dist-info/RECORD
