Metadata-Version: 2.4
Name: orpheus-cpp
Version: 0.0.3
Project-URL: Documentation, https://github.com/freddyaboulton/orpheus-cpp#readme
Project-URL: Issues, https://github.com/freddyaboulton/orpheus-cpp/issues
Project-URL: Source, https://github.com/freddyaboulton/orpheus-cpp
Author-email: Freddy Boulton <freddyboulton@notmyemail.com>
License-Expression: MIT
License-File: LICENSE.txt
Classifier: Development Status :: 4 - Beta
Classifier: Programming Language :: Python
Classifier: Programming Language :: Python :: 3.10
Classifier: Programming Language :: Python :: 3.11
Classifier: Programming Language :: Python :: 3.12
Classifier: Programming Language :: Python :: Implementation :: CPython
Classifier: Programming Language :: Python :: Implementation :: PyPy
Requires-Python: >=3.10
Requires-Dist: huggingface-hub
Requires-Dist: numpy>=2.0
Requires-Dist: onnxruntime
Requires-Dist: transformers
